qrandom/__init__.py
qrandom/qrandom.py
qrandom_NoahGWood-1.0.0.dist-info/METADATA
qrandom_NoahGWood-1.0.0.dist-info/RECORD
qrandom_NoahGWood-1.0.0.dist-info/WHEEL
qrandom_NoahGWood-1.0.0.dist-info/top_level.txt
