Metadata-Version: 2.1
Name: qrandom-NoahGWood
Version: 1.0.0
Summary: Shrodingers Random Number Generator
Home-page: https://github.com/NoahGWood/QRandom
Author: Noah Wood
Author-email: ngwood111@gmail.com
License: UNKNOWN
Platform: UNKNOWN
Classifier: Programming Language :: Python :: 3.6
Classifier: License :: OSI Approved :: GNU General Public License v3 (GPLv3)
Classifier: Operating System :: POSIX :: Linux
